{
  "experiment_name": "yacht_1080p120_phase1",
  "network": {
    "host": "192.168.0.17",
    "port": 5004,
    "rtp_payload_type": 96,
    "clock_rate": 90000,
    "jitterbuffer_latency_ms": 150,
    "mtu": 1300
  },
  "video_input": {
    "path": "/home/radxa/Videos/Samples/YachtRide_3840x2160_120fps_420_10bit_YUV.yuv",
    "width": 3840,
    "height": 2160,
    "source_framerate": 120,
    "framerate": 30,
    "format": "i420_10le",
    "bit_depth": 10
  },
  "video_input_backup": {
    "path": "/home/radxa/Videos/Samples/YachtRide_1920x1080_120fps_420_8bit_YUV.yuv",
    "width": 1920,
    "height": 1080,
    "source_framerate": 120,
    "framerate": 30,
    "format": "i420",
    "bit_depth": 8
  },
  "encoder": {
    "codec": "h265",
    "bitrate_kbps": 8000,
    "speed_preset": "veryfast",
    "tune": "zerolatency",
    "key_int_max": 120,
    "bframes": 0,
    "threads": 0,
    "software_h264_encoder": "x264enc",
    "software_h265_encoder": "x265enc",
    "hardware_encoders": {
      "h264": "nvh264enc",
      "h265": "nvh265enc"
    },
    "nvcodec_defaults": {
      "preset": "low-latency-hq",
      "rc_mode": "cbr",
      "zerolatency": true
    },
    "hardware_encoder_placeholder": {
      "enabled": false,
      "element": "auto",
      "notes": "默认使用软件编码器（x264/x265）。在有明确 NVIDIA/VAAPI 支持的环境中可手动启用硬件编码。"
    }
  },
  "sender": {
    "mode": "preencoded_mp4",
    "preencoded_mp4_path": "prepared/yacht_3840x2160_120fps_30fps_h265_8000kbps_10bit.mp4",
    "output_root": "output",
    "save_resolved_config": true,
    "save_run_info": true,
    "probe_max_buffers": 256,
    "csv_flush_interval": 60,
    "pts_jump_threshold_frames": 1.5
  },
  "receiver": {
    "mode": "full_stats",
    "use_vendor_plugins": false,
    "decode": true,
    "sink": "appsink",
    "sync": false,
    "output_root": "output",
    "save_resolved_config": true,
    "save_run_info": true,
    "appsink_max_buffers": 256,
    "appsink_drop": false,
    "post_decode_queue_max_buffers": 64,
    "csv_flush_interval": 60,
    "probe_sink_sync": false,
    "software_h264_decoder": "avdec_h264",
    "software_h265_decoder": "avdec_h265",
    "hardware_decoders": {
      "h264": "v4l2h264dec",
      "h265": "v4l2h265dec"
    },
    "hardware_decoder_placeholder": {
      "enabled": true,
      "element": "auto",
      "notes": "默认按 codec 自动选择 receiver.hardware_decoders 中的硬解元素；未配置时回退到 v4l2h264dec / v4l2h265dec。不同平台可替换为 mppvideodec, vaapih264dec 等。"
    }
  },
  "receiver_load": {
    "enabled": false,
    "startup_delay_sec": 2,
    "workdir": ".",
    "binary": "./vulkan_mem_press/vk_memstress",
    "args": [
      "--mb",
      "512",
      "--mode",
      "rdwr",
      "--stride",
      "16",
      "--iters",
      "200",
      "--chunk-iters",
      "40",
      "--einv",
      "128",
      "--wg",
      "4096",
      "--seconds",
      "45",
      "--spv",
      "./vulkan_mem_press/memstress.spv"
    ],
    "log_stdout": true
  },
  "stall_thresholds_ms": {
    "mode": "frame_intervals",
    "minor": 50,
    "major": 200,
    "minor_frame_intervals": 1.5,
    "major_frame_intervals": 3.0
  }
}